{
  "products": [
    {
      "buyLink": "https://zobovn.store/dat-hang",
      "badge": "Bán chạy",
      "price": "Liên hệ",
      "name": "Đầu lọc thuốc lá Full Size",
      "isBestSeller": true,
      "updatedAt": "2026-07-15T00:00:00.000Z",
      "isActive": true,
      "gallery": [
        {
          "type": "video",
          "url": "/assets/uploads/fv1.png",
          "title": "Ảnh hộp sản phẩm",
          "poster": "/assets/uploads/f6.webp"
        },
        {
          "type": "image",
          "url": "assets/products/full-size-5pcs.png",
          "title": "Bộ 5 đầu lọc"
        }
      ],
      "id": "full-size",
      "createdAt": "2026-07-15T00:00:00.000Z",
      "image": "/assets/uploads/f1.webp",
      "description": "Bộ 5 đầu lọc FulĐầu Lọc Thuốc Hộp ComBo 5 Chiếc, Sử Dụng Đa Năng FULLSIZE Cả 5 Đều Dùng Được Đầu Lớn & Vừa & Nhỏ , Tái Sử Dụng Nhiều Lần, Đầu lọc hút thuốc, đầu lọc hút thuốc lá, đầu lọc khói thuốcl Size, đóng gói gọn và dễ trưng bày.",
      "category": "Full Size"
    }
  ]
}
